hasher/__init__.py
hasher/__main__.py
hasher_cnml-0.0.2.dist-info/LICENSE
hasher_cnml-0.0.2.dist-info/METADATA
hasher_cnml-0.0.2.dist-info/WHEEL
hasher_cnml-0.0.2.dist-info/top_level.txt
hasher_cnml-0.0.2.dist-info/RECORD
